MANIFEST.in
README.rst
requirements-dev.txt
requirements.txt
setup.cfg
setup.py
Animate/Animation.py
Animate/Movie.py
Animate/__init__.py
Animate/checks.py
animateimages.egg-info/PKG-INFO
animateimages.egg-info/SOURCES.txt
animateimages.egg-info/dependency_links.txt
animateimages.egg-info/requires.txt
animateimages.egg-info/top_level.txt
test/test_Animation_init.py
test/test_add_annotations.py
test/test_add_axis.py
test/test_add_image.py
test/test_add_labels.py
test/test_save.py
test/test_ylim.py