Metadata-Version: 2.1
Name: animateimages
Version: 0.2.4
Summary: Animation of matplotlib images
Home-page: https://github.com/boazmohar/animateImages
Author: Boaz Mohar
Author-email: boazmohar@gmail.com
License: MIT
Download-URL: https://github.com/boazmohar/animateImages/archive/v0.2.4.tar.gz
Keywords: matplotlib,animation
Platform: UNKNOWN
Classifier: Development Status :: 3 - Alpha
Classifier: License :: OSI Approved :: MIT License
Classifier: Programming Language :: Python :: 2
Classifier: Programming Language :: Python :: 2.7
Classifier: Programming Language :: Python :: 3
Classifier: Programming Language :: Python :: 3.5
Classifier: Programming Language :: Python :: 3.6
Provides-Extra: dev
